{
	"description": "Cars by engine capacity",
	"data": [
		{
			"name": "Poland",
			"capacityTotal": 24360166,
			"capacityLow": 8430543,
			"capacityMedium": 12038405,
			"capacityHigh": 3891218
		},
		{
			"name": "Spain",
			"capacityTotal": 24558126,
			"capacityLow": 7164328,
			"capacityMedium": 15183946,
			"capacityHigh": 2209852
		},
		{
			"name": "Germany",
			"capacityTotal": 47715977,
			"capacityLow": 17257792,
			"capacityMedium": 22498307,
			"capacityHigh": 7959878
		},
		{
			"name": "France",
			"capacityTotal": 32416180,
			"capacityLow": 12528416,
			"capacityMedium": 19238054,
			"capacityHigh": 649710
		},
		{
			"name": "Norway",
			"capacityTotal": 2801208,
			"capacityLow": 470653,
			"capacityMedium": 1462410,
			"capacityHigh": 868145
		},
		{
			"name": "Sweden",
			"capacityTotal": 4887116,
			"capacityLow": 1574876,
			"capacityMedium": 2210784,
			"capacityHigh": 1101456
		},
		{
			"name": "Italy",
			"capacityTotal": 39545232,
			"capacityLow": 9584213,
			"capacityMedium": 26539487,
			"capacityHigh": 3421532
		}
	]
}
